mkdocs_awesome_autolinks/__init__.py
mkdocs_awesome_autolinks/plugin.py
mkdocs_awesome_autolinks-1.0.0.dist-info/licenses/LICENSE
mkdocs_awesome_autolinks-1.0.0.dist-info/METADATA
mkdocs_awesome_autolinks-1.0.0.dist-info/WHEEL
mkdocs_awesome_autolinks-1.0.0.dist-info/entry_points.txt
mkdocs_awesome_autolinks-1.0.0.dist-info/top_level.txt
mkdocs_awesome_autolinks-1.0.0.dist-info/RECORD
