Metadata-Version: 2.4
Name: mkdocs_awesome_autolinks
Version: 1.0.0
Summary: An MkDocs plugin for linking without specifying the full relative path and other features that ease using the file structure to generate navigation.
Author: Johan Boer
License: MIT
Project-URL: Homepage, https://github.com/Johan-EU/mkdocs-awesome-autolinks
Keywords: mkdocs,markdown,awesome,autolinks
Classifier: Topic :: Documentation
Classifier: Programming Language :: Python :: 3
Classifier: Development Status :: 5 - Production/Stable
Classifier: Intended Audience :: Developers
Classifier: Intended Audience :: Information Technology
Requires-Python: >=3.7
License-File: LICENSE
Requires-Dist: mkdocs>=1.4
Dynamic: license-file
